{
    "key": "group_5a37e01e4f32b",
    "title": "Category Attributes",
    "fields": [
        {
            "key": "field_5d024ba641baa",
            "label": "Background Image",
            "name": "acf-category_background_image",
            "type": "image",
            "instructions": "",
            "required": 0,
            "conditional_logic": 0,
            "wrapper": {
                "width": "",
                "class": "",
                "id": ""
            },
            "return_format": "array",
            "preview_size": "thumbnail",
            "library": "all",
            "min_width": "",
            "min_height": "",
            "min_size": "",
            "max_width": "",
            "max_height": "",
            "max_size": "",
            "mime_types": ""
        },
        {
            "key": "field_5cf314117dac4",
            "label": "Post Types",
            "name": "acf-category_post_types",
            "type": "taxonomy",
            "instructions": "Leave this field empty to display default Post Types",
            "required": 0,
            "conditional_logic": 0,
            "wrapper": {
                "width": "",
                "class": "",
                "id": ""
            },
            "taxonomy": "post_types_tax",
            "field_type": "multi_select",
            "allow_null": 0,
            "add_term": 0,
            "save_terms": 0,
            "load_terms": 0,
            "return_format": "object",
            "multiple": 0
        }
    ],
    "location": [
        [
            {
                "param": "taxonomy",
                "operator": "==",
                "value": "category"
            }
        ]
    ],
    "menu_order": 3,
    "position": "normal",
    "style": "default",
    "label_placement": "top",
    "instruction_placement": "label",
    "hide_on_screen": "",
    "active": 1,
    "description": "",
    "modified": 1560518021
}